{"trial_id": "13", "hyperparameters": {"space": [{"class_name": "Int", "config": {"name": "units", "default": null, "conditions": [], "min_value": 512, "max_value": 2048, "step": 256, "sampling": "linear"}}, {"class_name": "Float", "config": {"name": "dropout", "default": 0.1, "conditions": [], "min_value": 0.1, "max_value": 0.5, "step": 0.1, "sampling": "linear"}}, {"class_name": "Float", "config": {"name": "learning_rate", "default": 1e-05, "conditions": [], "min_value": 1e-05, "max_value": 0.01, "step": null, "sampling": "log"}}], "values": {"units": 1792, "dropout": 0.30000000000000004, "learning_rate": 0.0007171207855961936}}, "metrics": {"metrics": {"loss": {"direction": "min", "observations": [{"value": [0.378674974044164], "step": 3}]}, "accuracy": {"direction": "max", "observations": [{"value": [0.8578856190045675], "step": 3}]}, "precision": {"direction": "min", "observations": [{"value": [0.8832509318987528], "step": 3}]}, "recall": {"direction": "min", "observations": [{"value": [0.8272674679756165], "step": 3}]}, "val_loss": {"direction": "min", "observations": [{"value": [0.5845981041590372], "step": 3}]}, "val_accuracy": {"direction": "max", "observations": [{"value": [0.7849462429682413], "step": 3}]}, "val_precision": {"direction": "min", "observations": [{"value": [0.8108757734298706], "step": 3}]}, "val_recall": {"direction": "min", "observations": [{"value": [0.7607526779174805], "step": 3}]}}}, "score": 0.7849462429682413, "best_step": 3, "status": "COMPLETED", "message": null}